__init__.py
ezbroadcast.py
ezbroadcast-0.0.1.dist-info/LICENSE
ezbroadcast-0.0.1.dist-info/METADATA
ezbroadcast-0.0.1.dist-info/WHEEL
ezbroadcast-0.0.1.dist-info/top_level.txt
ezbroadcast-0.0.1.dist-info/RECORD
