Metadata-Version: 2.2
Name: ezbroadcast
Version: 0.0.1
Summary: Its the brodcast feture from scratch in python bacicly
Author-email: ocueye <carsonmayn@fuse.net>
Project-URL: Homepage, https://github.com/ocueye2/brodcast_ocueye
Project-URL: Issues, https://github.com/ocueye2/brodcast_ocueye/issues
Classifier: Programming Language :: Python :: 3
Classifier: Operating System :: OS Independent
Requires-Python: >=3.12
License-File: LICENSE
